osst/__init__.py
osst/libosst.abi3.so
osst/example.py
osst/.dylibs/libtbbmalloc.2.13.dylib
osst/.dylibs/libtbb.12.13.dylib
osst/.dylibs/libgmp.10.dylib
osst/model/metrics.py
osst/model/__init__.py
osst/model/encoder.py
osst/model/threshold_guess.py
osst/model/osst.py
osst/model/utils.py
osst/model/tree_survival_regressor.py
osst/model/imbalance/__init__.py
osst/model/imbalance/osdt_sup.py
osst/model/imbalance/rule.py
osst/model/imbalance/osdt_imb_v9.py
osst-0.1.8.dist-info/RECORD
osst-0.1.8.dist-info/LICENSE
osst-0.1.8.dist-info/WHEEL
osst-0.1.8.dist-info/top_level.txt
osst-0.1.8.dist-info/METADATA
